{"summary": {"recordClassId": 2, "type": "ALLROUND", "groups": [{"type": "CAREER_AVERAGES", "stats": [{"tt": "overview", "sp": "2012-2021", "mt": 37, "pr": null, "rn": 288, "wk": 54, "ct": 14, "st": 0, "hs": "50*", "hn": 0, "bbi": "6/29", "bta": 13.09, "bwa": 28.7, "fw": 2, "bbad": -15.61}]}, {"type": "OPPOSITION_TEAM", "stats": [{"tt": "v Afghanistan", "sp": "2018-2018", "mt": 1, "pr": "opposition=40", "rn": 2, "wk": 2, "ct": 1, "st": 0, "hs": "2", "hn": 0, "bbi": "2/39", "bta": 2, "bwa": 19.5, "fw": 0, "bbad": -17.5}, {"tt": "v Bangladesh", "sp": "2018-2019", "mt": 5, "pr": "opposition=25", "rn": 31, "wk": 6, "ct": 3, "st": 0, "hs": "17", "hn": 0, "bbi": "2/30", "bta": 10.33, "bwa": 25.5, "fw": 0, "bbad": -15.16}, {"tt": "v England", "sp": "2018-2018", "mt": 5, "pr": "opposition=1", "rn": 57, "wk": 9, "ct": 2, "st": 0, "hs": "32*", "hn": 0, "bbi": "4/19", "bta": 57, "bwa": 19.22, "fw": 0, "bbad": 37.77}, {"tt": "v India", "sp": "2017-2021", "mt": 8, "pr": "opposition=6", "rn": 43, "wk": 14, "ct": 0, "st": 0, "hs": "11*", "hn": 0, "bbi": "6/54", "bta": 8.6, "bwa": 26, "fw": 1, "bbad": -17.4}, {"tt": "v New Zealand", "sp": "2012-2012", "mt": 1, "pr": "opposition=5", "rn": null, "wk": null, "ct": null, "st": null, "hs": null, "hn": null, "bbi": null, "bta": null, "bwa": null, "fw": null, "bbad": null}, {"tt": "v Pakistan", "sp": "2017-2017", "mt": 4, "pr": "opposition=7", "rn": 70, "wk": 2, "ct": 3, "st": 0, "hs": "50*", "hn": 0, "bbi": "1/29", "bta": 23.33, "bwa": 83.5, "fw": 0, "bbad": -60.16}, {"tt": "v South Africa", "sp": "2018-2019", "mt": 9, "pr": "opposition=3", "rn": 70, "wk": 16, "ct": 4, "st": 0, "hs": "37", "hn": 0, "bbi": "6/29", "bta": 10, "bwa": 27.12, "fw": 1, "bbad": -17.12}, {"tt": "v Zimbabwe", "sp": "2017-2018", "mt": 4, "pr": "opposition=9", "rn": 15, "wk": 5, "ct": 1, "st": 0, "hs": "8", "hn": 0, "bbi": "4/47", "bta": 7.5, "bwa": 44, "fw": 0, "bbad": -36.5}]}, {"type": "HOST_COUNTRY", "stats": [{"tt": "in Bangladesh", "sp": "2018-2018", "mt": 5, "pr": "host=25", "rn": 39, "wk": 3, "ct": 4, "st": 0, "hs": "17", "hn": 0, "bbi": "2/30", "bta": 13, "bwa": 60.66, "fw": 0, "bbad": -47.66}, {"tt": "in India", "sp": "2017-2017", "mt": 3, "pr": "host=6", "rn": 12, "wk": 2, "ct": 0, "st": 0, "hs": "11", "hn": 0, "bbi": "1/7", "bta": 6, "bwa": 55.5, "fw": 0, "bbad": -49.5}, {"tt": "in South Africa", "sp": "2019-2019", "mt": 4, "pr": "host=3", "rn": 7, "wk": 2, "ct": 1, "st": 0, "hs": "4", "hn": 0, "bbi": "1/38", "bta": 2.33, "bwa": 92, "fw": 0, "bbad": -89.66}, {"tt": "in Sri Lanka", "sp": "2012-2021", "mt": 20, "pr": "host=8", "rn": 158, "wk": 43, "ct": 5, "st": 0, "hs": "37", "hn": 0, "bbi": "6/29", "bta": 15.8, "bwa": 20.16, "fw": 2, "bbad": -4.36}, {"tt": "in U.A.E.", "sp": "2017-2018", "mt": 5, "pr": "host=27", "rn": 72, "wk": 4, "ct": 4, "st": 0, "hs": "50*", "hn": 0, "bbi": "2/39", "bta": 18, "bwa": 51.5, "fw": 0, "bbad": -33.5}]}, {"type": "CONTINENT", "stats": [{"tt": "in Africa", "sp": "2019-2019", "mt": 4, "pr": "continent=1", "rn": 7, "wk": 2, "ct": 1, "st": 0, "hs": "4", "hn": 0, "bbi": "1/38", "bta": 2.33, "bwa": 92, "fw": 0, "bbad": -89.66}, {"tt": "in Asia", "sp": "2012-2021", "mt": 33, "pr": "continent=2", "rn": 281, "wk": 52, "ct": 13, "st": 0, "hs": "50*", "hn": 0, "bbi": "6/29", "bta": 14.78, "bwa": 26.26, "fw": 2, "bbad": -11.47}]}, {"type": "HOME_OR_AWAY", "stats": [{"tt": "home", "sp": "2012-2021", "mt": 20, "pr": "home_or_away=1", "rn": 158, "wk": 43, "ct": 5, "st": 0, "hs": "37", "hn": 0, "bbi": "6/29", "bta": 15.8, "bwa": 20.16, "fw": 2, "bbad": -4.36}, {"tt": "away", "sp": "2017-2019", "mt": 10, "pr": "home_or_away=2", "rn": 50, "wk": 7, "ct": 4, "st": 0, "hs": "17", "hn": 0, "bbi": "2/30", "bta": 7.14, "bwa": 52.14, "fw": 0, "bbad": -45}, {"tt": "neutral", "sp": "2017-2018", "mt": 7, "pr": "home_or_away=3", "rn": 80, "wk": 4, "ct": 5, "st": 0, "hs": "50*", "hn": 0, "bbi": "2/39", "bta": 16, "bwa": 79.5, "fw": 0, "bbad": -63.5}]}, {"type": "YEAR", "stats": [{"tt": "year 2012", "sp": null, "mt": 1, "pr": "year=2012", "rn": null, "wk": null, "ct": null, "st": null, "hs": null, "hn": null, "bbi": null, "bta": null, "bwa": null, "fw": null, "bbad": null}, {"tt": "year 2017", "sp": null, "mt": 13, "pr": "year=2017", "rn": 115, "wk": 18, "ct": 3, "st": 0, "hs": "50*", "hn": 0, "bbi": "6/54", "bta": 12.77, "bwa": 33.05, "fw": 1, "bbad": -20.27}, {"tt": "year 2018", "sp": null, "mt": 16, "pr": "year=2018", "rn": 161, "wk": 28, "ct": 10, "st": 0, "hs": "37", "hn": 0, "bbi": "6/29", "bta": 17.88, "bwa": 23, "fw": 1, "bbad": -5.11}, {"tt": "year 2019", "sp": null, "mt": 6, "pr": "year=2019", "rn": 7, "wk": 5, "ct": 1, "st": 0, "hs": "4", "hn": 0, "bbi": "2/39", "bta": 1.75, "bwa": 53.4, "fw": 0, "bbad": -51.65}, {"tt": "year 2021", "sp": null, "mt": 1, "pr": "year=2021", "rn": 5, "wk": 3, "ct": 0, "st": 0, "hs": "5*", "hn": 0, "bbi": "3/44", "bta": null, "bwa": 14.66, "fw": 0, "bbad": null}]}, {"type": "SEASON", "stats": [{"tt": "season 2012/13", "sp": null, "mt": 1, "pr": "season=2012/13", "rn": null, "wk": null, "ct": null, "st": null, "hs": null, "hn": null, "bbi": null, "bta": null, "bwa": null, "fw": null, "bbad": null}, {"tt": "season 2017", "sp": null, "mt": 6, "pr": "season=2017", "rn": 33, "wk": 14, "ct": 0, "st": 0, "hs": "11*", "hn": 0, "bbi": "6/54", "bta": 8.25, "bwa": 22.64, "fw": 1, "bbad": -14.39}, {"tt": "season 2017/18", "sp": null, "mt": 12, "pr": "season=2017/18", "rn": 121, "wk": 7, "ct": 7, "st": 0, "hs": "50*", "hn": 0, "bbi": "2/30", "bta": 15.12, "bwa": 65.71, "fw": 0, "bbad": -50.58}, {"tt": "season 2018", "sp": null, "mt": 6, "pr": "season=2018", "rn": 65, "wk": 16, "ct": 4, "st": 0, "hs": "37", "hn": 0, "bbi": "6/29", "bta": 13, "bwa": 18.06, "fw": 1, "bbad": -5.06}, {"tt": "season 2018/19", "sp": null, "mt": 9, "pr": "season=2018/19", "rn": 64, "wk": 11, "ct": 3, "st": 0, "hs": "32*", "hn": 0, "bbi": "4/19", "bta": 16, "bwa": 32.45, "fw": 0, "bbad": -16.45}, {"tt": "season 2019", "sp": null, "mt": 2, "pr": "season=2019", "rn": 0, "wk": 3, "ct": 0, "st": 0, "hs": "0", "hn": 0, "bbi": "2/39", "bta": 0, "bwa": 27.66, "fw": 0, "bbad": -27.66}, {"tt": "season 2021", "sp": null, "mt": 1, "pr": "season=2021", "rn": 5, "wk": 3, "ct": 0, "st": 0, "hs": "5*", "hn": 0, "bbi": "3/44", "bta": null, "bwa": 14.66, "fw": 0, "bbad": null}]}, {"type": "CAPTAINS_INVOLVED", "stats": [{"tt": "*LD Chandimal", "sp": "2018-2018", "mt": 9, "pr": "captain_involve=52371", "rn": 88, "wk": 12, "ct": 5, "st": 0, "hs": "32*", "hn": 0, "bbi": "4/19", "bta": 29.33, "bwa": 24, "fw": 0, "bbad": 5.33}, {"tt": "*DPMD Jayawardene", "sp": "2012-2012", "mt": 1, "pr": "captain_involve=6315", "rn": null, "wk": null, "ct": null, "st": null, "hs": null, "hn": null, "bbi": null, "bta": null, "bwa": null, "fw": null, "bbad": null}, {"tt": "*CK Kapugedera", "sp": "2017-2017", "mt": 1, "pr": "captain_involve=48520", "rn": 2, "wk": 2, "ct": 0, "st": 0, "hs": "2", "hn": 0, "bbi": "2/38", "bta": 2, "bwa": 19, "fw": 0, "bbad": -17}, {"tt": "*FDM Karunaratne", "sp": "2019-2019", "mt": 2, "pr": "captain_involve=48988", "rn": 0, "wk": 3, "ct": 0, "st": 0, "hs": "0", "hn": 0, "bbi": "2/39", "bta": 0, "bwa": 27.66, "fw": 0, "bbad": -27.66}, {"tt": "*SL Malinga", "sp": "2017-2019", "mt": 5, "pr": "captain_involve=45105", "rn": 18, "wk": 3, "ct": 1, "st": 0, "hs": "11*", "hn": 0, "bbi": "1/38", "bta": 6, "bwa": 84, "fw": 0, "bbad": -78}, {"tt": "*AD Mathews", "sp": "2017-2018", "mt": 9, "pr": "captain_involve=47023", "rn": 80, "wk": 21, "ct": 5, "st": 0, "hs": "37", "hn": 0, "bbi": "6/29", "bta": 11.42, "bwa": 22.09, "fw": 1, "bbad": -10.66}, {"tt": "*NLTC Perera", "sp": "2017-2017", "mt": 3, "pr": "captain_involve=49193", "rn": 12, "wk": 2, "ct": 0, "st": 0, "hs": "11", "hn": 0, "bbi": "1/7", "bta": 6, "bwa": 55.5, "fw": 0, "bbad": -49.5}, {"tt": "*MD Shanaka", "sp": "2021-2021", "mt": 1, "pr": "captain_involve=61690", "rn": 5, "wk": 3, "ct": 0, "st": 0, "hs": "5*", "hn": 0, "bbi": "3/44", "bta": null, "bwa": 14.66, "fw": 0, "bbad": null}, {"tt": "*WU Tharanga", "sp": "2017-2017", "mt": 6, "pr": "captain_involve=11334", "rn": 83, "wk": 8, "ct": 3, "st": 0, "hs": "50*", "hn": 0, "bbi": "6/54", "bta": 16.6, "bwa": 33.75, "fw": 1, "bbad": -17.15}]}, {"type": "CAPTAIN", "stats": [{"tt": "is not captain", "sp": "2012-2021", "mt": 37, "pr": "captain=0", "rn": 288, "wk": 54, "ct": 14, "st": 0, "hs": "50*", "hn": 0, "bbi": "6/29", "bta": 13.09, "bwa": 28.7, "fw": 2, "bbad": -15.61}]}, {"type": "KEEPER", "stats": [{"tt": "is not keeper", "sp": "2012-2021", "mt": 37, "pr": "keeper=0", "rn": 288, "wk": 54, "ct": 14, "st": 0, "hs": "50*", "hn": 0, "bbi": "6/29", "bta": 13.09, "bwa": 28.7, "fw": 2, "bbad": -15.61}]}, {"type": "TOSS", "stats": [{"tt": "won the toss", "sp": "2017-2019", "mt": 21, "pr": "toss=1", "rn": 198, "wk": 29, "ct": 11, "st": 0, "hs": "50*", "hn": 0, "bbi": "6/29", "bta": 14.14, "bwa": 32.72, "fw": 1, "bbad": -18.58}, {"tt": "lost the toss", "sp": "2012-2021", "mt": 16, "pr": "toss=2", "rn": 90, "wk": 25, "ct": 3, "st": 0, "hs": "32*", "hn": 0, "bbi": "6/54", "bta": 11.25, "bwa": 24.04, "fw": 1, "bbad": -12.79}]}, {"type": "BATTING_FIELDING_SEQUENCE_AND_TOSS", "stats": [{"tt": "won toss &amp; batted", "sp": "2017-2019", "mt": 12, "pr": "batting_fielding_first=1;toss=1", "rn": 88, "wk": 23, "ct": 5, "st": 0, "hs": "18*", "hn": 0, "bbi": "6/29", "bta": 8.8, "bwa": 21.91, "fw": 1, "bbad": -13.11}, {"tt": "won toss &amp; fielded", "sp": "2017-2019", "mt": 9, "pr": "batting_fielding_first=2;toss=1", "rn": 110, "wk": 6, "ct": 6, "st": 0, "hs": "50*", "hn": 0, "bbi": "1/7", "bta": 27.5, "bwa": 74.16, "fw": 0, "bbad": -46.66}, {"tt": "lost toss &amp; sent in", "sp": "2012-2019", "mt": 8, "pr": "batting_fielding_first=1;toss=2", "rn": 57, "wk": 16, "ct": 0, "st": 0, "hs": "32*", "hn": 0, "bbi": "6/54", "bta": 11.4, "bwa": 18.5, "fw": 1, "bbad": -7.1}, {"tt": "lost toss &amp; fielded", "sp": "2017-2021", "mt": 8, "pr": "batting_fielding_first=2;toss=2", "rn": 33, "wk": 9, "ct": 3, "st": 0, "hs": "14", "hn": 0, "bbi": "3/44", "bta": 11, "bwa": 33.88, "fw": 0, "bbad": -22.88}]}, {"type": "BATTING_FIELDING_SEQUENCE", "stats": [{"tt": "matches batting first", "sp": "2012-2019", "mt": 20, "pr": "batting_fielding_first=1", "rn": 145, "wk": 39, "ct": 5, "st": 0, "hs": "32*", "hn": 0, "bbi": "6/29", "bta": 9.66, "bwa": 20.51, "fw": 2, "bbad": -10.84}, {"tt": "matches fielding first", "sp": "2017-2021", "mt": 17, "pr": "batting_fielding_first=2", "rn": 143, "wk": 15, "ct": 9, "st": 0, "hs": "50*", "hn": 0, "bbi": "3/44", "bta": 20.42, "bwa": 50, "fw": 0, "bbad": -29.57}]}, {"type": "TEAM_INNINGS", "stats": [{"tt": "1st team innings", "sp": "2012-2021", "mt": 37, "pr": "innings_number=1;innings_number=2", "rn": 288, "wk": 54, "ct": 14, "st": 0, "hs": "50*", "hn": 0, "bbi": "6/29", "bta": 13.09, "bwa": 28.7, "fw": 2, "bbad": -15.61}]}, {"type": "MATCH_INNINGS", "stats": [{"tt": "1st match innings", "sp": "2012-2021", "mt": 37, "pr": "innings_number=1", "rn": 145, "wk": 15, "ct": 9, "st": 0, "hs": "32*", "hn": 0, "bbi": "3/44", "bta": 9.66, "bwa": 50, "fw": 0, "bbad": -40.33}, {"tt": "2nd match innings", "sp": "2017-2021", "mt": 35, "pr": "innings_number=2", "rn": 143, "wk": 39, "ct": 5, "st": 0, "hs": "50*", "hn": 0, "bbi": "6/29", "bta": 20.42, "bwa": 20.51, "fw": 2, "bbad": -0.08}]}, {"type": "FLOODLIT", "stats": [{"tt": "day match", "sp": "2017-2019", "mt": 9, "pr": "floodlit=1", "rn": 89, "wk": 15, "ct": 3, "st": 0, "hs": "37", "hn": 0, "bbi": "4/47", "bta": 17.8, "bwa": 31.8, "fw": 0, "bbad": -14}, {"tt": "day/night match", "sp": "2012-2021", "mt": 28, "pr": "floodlit=2", "rn": 199, "wk": 39, "ct": 11, "st": 0, "hs": "50*", "hn": 0, "bbi": "6/29", "bta": 11.7, "bwa": 27.51, "fw": 2, "bbad": -15.8}]}, {"type": "RESULT", "stats": [{"tt": "won match", "sp": "2017-2021", "mt": 10, "pr": "result=1", "rn": 46, "wk": 20, "ct": 3, "st": 0, "hs": "18*", "hn": 0, "bbi": "6/29", "bta": 15.33, "bwa": 14.35, "fw": 1, "bbad": 0.98}, {"tt": "lost match", "sp": "2017-2019", "mt": 25, "pr": "result=2", "rn": 242, "wk": 33, "ct": 11, "st": 0, "hs": "50*", "hn": 0, "bbi": "6/54", "bta": 12.73, "bwa": 37.36, "fw": 1, "bbad": -24.62}, {"tt": "no result", "sp": "2012-2018", "mt": 2, "pr": "result=5", "rn": null, "wk": 1, "ct": 0, "st": 0, "hs": null, "hn": null, "bbi": "1/30", "bta": null, "bwa": 30, "fw": 0, "bbad": null}]}, {"type": "BATTING_FIELDING_SEQUENCE_AND_RESULT", "stats": [{"tt": "won batting first", "sp": "2018-2019", "mt": 5, "pr": "batting_fielding_first=1;result=1", "rn": 41, "wk": 14, "ct": 3, "st": 0, "hs": "18*", "hn": 0, "bbi": "6/29", "bta": 13.66, "bwa": 10.85, "fw": 1, "bbad": 2.8}, {"tt": "won fielding first", "sp": "2017-2021", "mt": 5, "pr": "batting_fielding_first=2;result=1", "rn": 5, "wk": 6, "ct": 0, "st": 0, "hs": "5*", "hn": 0, "bbi": "3/44", "bta": null, "bwa": 22.5, "fw": 0, "bbad": null}, {"tt": "lost batting first", "sp": "2017-2019", "mt": 14, "pr": "batting_fielding_first=1;result=2", "rn": 104, "wk": 25, "ct": 2, "st": 0, "hs": "32*", "hn": 0, "bbi": "6/54", "bta": 8.66, "bwa": 25.92, "fw": 1, "bbad": -17.25}, {"tt": "lost fielding first", "sp": "2017-2019", "mt": 11, "pr": "batting_fielding_first=2;result=2", "rn": 138, "wk": 8, "ct": 9, "st": 0, "hs": "50*", "hn": 0, "bbi": "2/39", "bta": 19.71, "bwa": 73.12, "fw": 0, "bbad": -53.41}, {"tt": "no result batting first", "sp": "2012-2012", "mt": 1, "pr": "batting_fielding_first=1;result=5", "rn": null, "wk": null, "ct": null, "st": null, "hs": null, "hn": null, "bbi": null, "bta": null, "bwa": null, "fw": null, "bbad": null}, {"tt": "no result fielding first", "sp": "2018-2018", "mt": 1, "pr": "batting_fielding_first=2;result=5", "rn": null, "wk": 1, "ct": 0, "st": 0, "hs": null, "hn": null, "bbi": "1/30", "bta": null, "bwa": 30, "fw": 0, "bbad": null}]}, {"type": "TOURNAMENT_TYPE", "stats": [{"tt": "2 team series", "sp": "2012-2021", "mt": 31, "pr": "tournament_type=2", "rn": 247, "wk": 49, "ct": 9, "st": 0, "hs": "50*", "hn": 0, "bbi": "6/29", "bta": 13.72, "bwa": 27.12, "fw": 2, "bbad": -13.4}, {"tt": "3-4 team tournaments", "sp": "2018-2018", "mt": 5, "pr": "tournament_type=3", "rn": 39, "wk": 3, "ct": 4, "st": 0, "hs": "17", "hn": 0, "bbi": "2/30", "bta": 13, "bwa": 60.66, "fw": 0, "bbad": -47.66}, {"tt": "5+ team tournaments", "sp": "2018-2021", "mt": 2, "pr": "tournament_type=5", "rn": 7, "wk": 5, "ct": 1, "st": 0, "hs": "5*", "hn": 0, "bbi": "3/44", "bta": 7, "bwa": 16.6, "fw": 0, "bbad": -9.6}]}, {"type": "MATCH_NUMBER", "stats": [{"tt": "1st match in series", "sp": "2017-2019", "mt": 6, "pr": "match_number=1", "rn": 61, "wk": 8, "ct": 2, "st": 0, "hs": "50*", "hn": 0, "bbi": "3/50", "bta": 30.5, "bwa": 31.37, "fw": 0, "bbad": -0.87}, {"tt": "2nd match in series", "sp": "2017-2019", "mt": 7, "pr": "match_number=2", "rn": 34, "wk": 13, "ct": 6, "st": 0, "hs": "11", "hn": 0, "bbi": "6/54", "bta": 6.8, "bwa": 25.84, "fw": 1, "bbad": -19.04}, {"tt": "3rd match in series", "sp": "2017-2021", "mt": 8, "pr": "match_number=3", "rn": 53, "wk": 9, "ct": 0, "st": 0, "hs": "37", "hn": 0, "bbi": "3/44", "bta": 8.83, "bwa": 45.11, "fw": 0, "bbad": -36.27}, {"tt": "4th match in series", "sp": "2017-2018", "mt": 4, "pr": "match_number=4", "rn": 62, "wk": 5, "ct": 0, "st": 0, "hs": "32*", "hn": 0, "bbi": "2/27", "bta": 62, "bwa": 30.8, "fw": 0, "bbad": 31.2}, {"tt": "5th match in series", "sp": "2012-2019", "mt": 6, "pr": "match_number=5", "rn": 37, "wk": 14, "ct": 1, "st": 0, "hs": "18*", "hn": 0, "bbi": "6/29", "bta": 9.25, "bwa": 13, "fw": 1, "bbad": -3.75}]}, {"type": "MAJOR_TROPHY", "stats": [{"tt": "Asia Cup", "sp": "2018-2018", "mt": 1, "pr": "trophy=14", "rn": 2, "wk": 2, "ct": 1, "st": 0, "hs": "2", "hn": 0, "bbi": "2/39", "bta": 2, "bwa": 19.5, "fw": 0, "bbad": -17.5}]}, {"type": "FINAL_TYPE", "stats": [{"tt": "tournament finals", "sp": "2018-2018", "mt": 1, "pr": "final_type=1", "rn": 17, "wk": 2, "ct": 2, "st": 0, "hs": "17", "hn": 0, "bbi": "2/30", "bta": 17, "bwa": 15, "fw": 0, "bbad": 2}, {"tt": "preliminary matches", "sp": "2018-2021", "mt": 6, "pr": "final_type=0", "rn": 29, "wk": 6, "ct": 3, "st": 0, "hs": "14", "hn": 0, "bbi": "3/44", "bta": 9.66, "bwa": 39.16, "fw": 0, "bbad": -29.5}]}]}}