{"summary": {"recordClassId": 2, "type": "BOWLING", "groups": [{"type": "CAREER_AVERAGES", "stats": [{"bl": null, "tt": "overview", "sp": "2018-2020", "mt": 13, "in": 13, "pr": null, "ov": 118, "cd": 690, "md": 11, "wk": 24, "fwk": 1, "fw": 0, "tw": 0, "bbi": "4/26", "bbm": "4/26", "bwa": 28.75, "bwe": 5.84, "bwsr": 29.5}]}, {"type": "OPPOSITION_TEAM", "stats": [{"bl": null, "tt": "vs England", "sp": "2018-2018", "mt": 4, "in": 4, "pr": "opposition=1", "ov": 37, "cd": 271, "md": 2, "wk": 7, "fwk": 0, "fw": 0, "tw": 0, "bbi": "3/92", "bbm": "3/92", "bwa": 38.71, "bwe": 7.32, "bwsr": 31.7}, {"bl": null, "tt": "vs India", "sp": "2019-2019", "mt": 6, "in": 6, "pr": "opposition=6", "ov": 58, "cd": 281, "md": 5, "wk": 14, "fwk": 1, "fw": 0, "tw": 0, "bbi": "4/26", "bbm": "4/26", "bwa": 20.07, "bwe": 4.84, "bwsr": 24.8}, {"bl": null, "tt": "vs Pakistan", "sp": "2019-2019", "mt": 2, "in": 2, "pr": "opposition=7", "ov": 13, "cd": 80, "md": 3, "wk": 3, "fwk": 0, "fw": 0, "tw": 0, "bbi": "2/16", "bbm": "2/16", "bwa": 26.66, "bwe": 6.15, "bwsr": 26}, {"bl": null, "tt": "vs South Africa", "sp": "2020-2020", "mt": 1, "in": 1, "pr": "opposition=3", "ov": 10, "cd": 58, "md": 1, "wk": 0, "fwk": 0, "fw": 0, "tw": 0, "bbi": null, "bbm": null, "bwa": null, "bwe": 5.8, "bwsr": null}]}, {"type": "HOST_COUNTRY", "stats": [{"bl": null, "tt": "in Australia", "sp": "2018-2019", "mt": 4, "in": 4, "pr": "host=2", "ov": 40, "cd": 169, "md": 4, "wk": 8, "fwk": 1, "fw": 0, "tw": 0, "bbi": "4/26", "bbm": "4/26", "bwa": 21.12, "bwe": 4.22, "bwsr": 30}, {"bl": null, "tt": "in England", "sp": "2018-2018", "mt": 3, "in": 3, "pr": "host=1", "ov": 27, "cd": 214, "md": 1, "wk": 5, "fwk": 0, "fw": 0, "tw": 0, "bbi": "3/92", "bbm": "3/92", "bwa": 42.8, "bwe": 7.92, "bwsr": 32.4}, {"bl": null, "tt": "in India", "sp": "2019-2019", "mt": 3, "in": 3, "pr": "host=6", "ov": 28, "cd": 169, "md": 2, "wk": 8, "fwk": 0, "fw": 0, "tw": 0, "bbi": "3/37", "bbm": "3/37", "bwa": 21.12, "bwe": 6.03, "bwsr": 21}, {"bl": null, "tt": "in South Africa", "sp": "2020-2020", "mt": 1, "in": 1, "pr": "host=3", "ov": 10, "cd": 58, "md": 1, "wk": 0, "fwk": 0, "fw": 0, "tw": 0, "bbi": null, "bbm": null, "bwa": null, "bwe": 5.8, "bwsr": null}, {"bl": null, "tt": "in U.A.E.", "sp": "2019-2019", "mt": 2, "in": 2, "pr": "host=27", "ov": 13, "cd": 80, "md": 3, "wk": 3, "fwk": 0, "fw": 0, "tw": 0, "bbi": "2/16", "bbm": "2/16", "bwa": 26.66, "bwe": 6.15, "bwsr": 26}]}, {"type": "CONTINENT", "stats": [{"bl": null, "tt": "in Africa", "sp": "2020-2020", "mt": 1, "in": 1, "pr": "continent=1", "ov": 10, "cd": 58, "md": 1, "wk": 0, "fwk": 0, "fw": 0, "tw": 0, "bbi": null, "bbm": null, "bwa": null, "bwe": 5.8, "bwsr": null}, {"bl": null, "tt": "in Asia", "sp": "2019-2019", "mt": 5, "in": 5, "pr": "continent=2", "ov": 41, "cd": 249, "md": 5, "wk": 11, "fwk": 0, "fw": 0, "tw": 0, "bbi": "3/37", "bbm": "3/37", "bwa": 22.63, "bwe": 6.07, "bwsr": 22.3}, {"bl": null, "tt": "in Europe", "sp": "2018-2018", "mt": 3, "in": 3, "pr": "continent=4", "ov": 27, "cd": 214, "md": 1, "wk": 5, "fwk": 0, "fw": 0, "tw": 0, "bbi": "3/92", "bbm": "3/92", "bwa": 42.8, "bwe": 7.92, "bwsr": 32.4}, {"bl": null, "tt": "in Oceania", "sp": "2018-2019", "mt": 4, "in": 4, "pr": "continent=5", "ov": 40, "cd": 169, "md": 4, "wk": 8, "fwk": 1, "fw": 0, "tw": 0, "bbi": "4/26", "bbm": "4/26", "bwa": 21.12, "bwe": 4.22, "bwsr": 30}]}, {"type": "HOME_OR_AWAY", "stats": [{"bl": null, "tt": "home", "sp": "2018-2019", "mt": 4, "in": 4, "pr": "home_or_away=1", "ov": 40, "cd": 169, "md": 4, "wk": 8, "fwk": 1, "fw": 0, "tw": 0, "bbi": "4/26", "bbm": "4/26", "bwa": 21.12, "bwe": 4.22, "bwsr": 30}, {"bl": null, "tt": "away", "sp": "2018-2020", "mt": 7, "in": 7, "pr": "home_or_away=2", "ov": 65, "cd": 441, "md": 4, "wk": 13, "fwk": 0, "fw": 0, "tw": 0, "bbi": "3/37", "bbm": "3/37", "bwa": 33.92, "bwe": 6.78, "bwsr": 30}, {"bl": null, "tt": "neutral", "sp": "2019-2019", "mt": 2, "in": 2, "pr": "home_or_away=3", "ov": 13, "cd": 80, "md": 3, "wk": 3, "fwk": 0, "fw": 0, "tw": 0, "bbi": "2/16", "bbm": "2/16", "bwa": 26.66, "bwe": 6.15, "bwsr": 26}]}, {"type": "YEAR", "stats": [{"bl": null, "tt": "year 2018", "sp": null, "mt": 4, "in": 4, "pr": "year=2018", "ov": 37, "cd": 271, "md": 2, "wk": 7, "fwk": 0, "fw": 0, "tw": 0, "bbi": "3/92", "bbm": "3/92", "bwa": 38.71, "bwe": 7.32, "bwsr": 31.7}, {"bl": null, "tt": "year 2019", "sp": null, "mt": 8, "in": 8, "pr": "year=2019", "ov": 71, "cd": 361, "md": 8, "wk": 17, "fwk": 1, "fw": 0, "tw": 0, "bbi": "4/26", "bbm": "4/26", "bwa": 21.23, "bwe": 5.08, "bwsr": 25}, {"bl": null, "tt": "year 2020", "sp": null, "mt": 1, "in": 1, "pr": "year=2020", "ov": 10, "cd": 58, "md": 1, "wk": 0, "fwk": 0, "fw": 0, "tw": 0, "bbi": null, "bbm": null, "bwa": null, "bwe": 5.8, "bwsr": null}]}, {"type": "SEASON", "stats": [{"bl": null, "tt": "season 2017/18", "sp": null, "mt": 1, "in": 1, "pr": "season=2017/18", "ov": 10, "cd": 57, "md": 1, "wk": 2, "fwk": 0, "fw": 0, "tw": 0, "bbi": "2/57", "bbm": "2/57", "bwa": 28.5, "bwe": 5.7, "bwsr": 30}, {"bl": null, "tt": "season 2018", "sp": null, "mt": 3, "in": 3, "pr": "season=2018", "ov": 27, "cd": 214, "md": 1, "wk": 5, "fwk": 0, "fw": 0, "tw": 0, "bbi": "3/92", "bbm": "3/92", "bwa": 42.8, "bwe": 7.92, "bwsr": 32.4}, {"bl": null, "tt": "season 2018/19", "sp": null, "mt": 8, "in": 8, "pr": "season=2018/19", "ov": 71, "cd": 361, "md": 8, "wk": 17, "fwk": 1, "fw": 0, "tw": 0, "bbi": "4/26", "bbm": "4/26", "bwa": 21.23, "bwe": 5.08, "bwsr": 25}, {"bl": null, "tt": "season 2019/20", "sp": null, "mt": 1, "in": 1, "pr": "season=2019/20", "ov": 10, "cd": 58, "md": 1, "wk": 0, "fwk": 0, "fw": 0, "tw": 0, "bbi": null, "bbm": null, "bwa": null, "bwe": 5.8, "bwsr": null}]}, {"type": "CAPTAINS_INVOLVED", "stats": [{"bl": null, "tt": "*AJ Finch", "sp": "2019-2020", "mt": 9, "in": 9, "pr": "captain_involve=35812", "ov": 81, "cd": 419, "md": 9, "wk": 17, "fwk": 1, "fw": 0, "tw": 0, "bbi": "4/26", "bbm": "4/26", "bwa": 24.64, "bwe": 5.17, "bwsr": 28.5}, {"bl": null, "tt": "*TD Paine", "sp": "2018-2018", "mt": 3, "in": 3, "pr": "captain_involve=34747", "ov": 27, "cd": 214, "md": 1, "wk": 5, "fwk": 0, "fw": 0, "tw": 0, "bbi": "3/92", "bbm": "3/92", "bwa": 42.8, "bwe": 7.92, "bwsr": 32.4}, {"bl": null, "tt": "*SPD Smith", "sp": "2018-2018", "mt": 1, "in": 1, "pr": "captain_involve=50281", "ov": 10, "cd": 57, "md": 1, "wk": 2, "fwk": 0, "fw": 0, "tw": 0, "bbi": "2/57", "bbm": "2/57", "bwa": 28.5, "bwe": 5.7, "bwsr": 30}]}, {"type": "CAPTAIN", "stats": [{"bl": null, "tt": "is not captain", "sp": "2018-2020", "mt": 13, "in": 13, "pr": "captain=0", "ov": 118, "cd": 690, "md": 11, "wk": 24, "fwk": 1, "fw": 0, "tw": 0, "bbi": "4/26", "bbm": "4/26", "bwa": 28.75, "bwe": 5.84, "bwsr": 29.5}]}, {"type": "KEEPER", "stats": [{"bl": null, "tt": "is not keeper", "sp": "2018-2020", "mt": 13, "in": 13, "pr": "keeper=0", "ov": 118, "cd": 690, "md": 11, "wk": 24, "fwk": 1, "fw": 0, "tw": 0, "bbi": "4/26", "bbm": "4/26", "bwa": 28.75, "bwe": 5.84, "bwsr": 29.5}]}, {"type": "TOSS", "stats": [{"bl": null, "tt": "won the toss", "sp": "2018-2019", "mt": 7, "in": 7, "pr": "toss=1", "ov": 67, "cd": 403, "md": 4, "wk": 14, "fwk": 1, "fw": 0, "tw": 0, "bbi": "4/26", "bbm": "4/26", "bwa": 28.78, "bwe": 6.01, "bwsr": 28.7}, {"bl": null, "tt": "lost the toss", "sp": "2019-2020", "mt": 6, "in": 6, "pr": "toss=2", "ov": 51, "cd": 287, "md": 7, "wk": 10, "fwk": 0, "fw": 0, "tw": 0, "bbi": "3/37", "bbm": "3/37", "bwa": 28.7, "bwe": 5.62, "bwsr": 30.6}]}, {"type": "BATTING_FIELDING_SEQUENCE_AND_TOSS", "stats": [{"bl": null, "tt": "won toss &amp; batted", "sp": "2018-2019", "mt": 5, "in": 5, "pr": "batting_fielding_first=1;toss=1", "ov": 47, "cd": 247, "md": 3, "wk": 9, "fwk": 1, "fw": 0, "tw": 0, "bbi": "4/26", "bbm": "4/26", "bwa": 27.44, "bwe": 5.25, "bwsr": 31.3}, {"bl": null, "tt": "won toss &amp; fielded", "sp": "2018-2018", "mt": 2, "in": 2, "pr": "batting_fielding_first=2;toss=1", "ov": 20, "cd": 156, "md": 1, "wk": 5, "fwk": 0, "fw": 0, "tw": 0, "bbi": "3/92", "bbm": "3/92", "bwa": 31.2, "bwe": 7.8, "bwsr": 24}, {"bl": null, "tt": "lost toss &amp; sent in", "sp": "2019-2020", "mt": 3, "in": 3, "pr": "batting_fielding_first=1;toss=2", "ov": 29, "cd": 122, "md": 4, "wk": 4, "fwk": 0, "fw": 0, "tw": 0, "bbi": "3/37", "bbm": "3/37", "bwa": 30.5, "bwe": 4.2, "bwsr": 43.5}, {"bl": null, "tt": "lost toss &amp; fielded", "sp": "2019-2019", "mt": 3, "in": 3, "pr": "batting_fielding_first=2;toss=2", "ov": 22, "cd": 165, "md": 3, "wk": 6, "fwk": 0, "fw": 0, "tw": 0, "bbi": "3/85", "bbm": "3/85", "bwa": 27.5, "bwe": 7.5, "bwsr": 22}]}, {"type": "BATTING_FIELDING_SEQUENCE", "stats": [{"bl": null, "tt": "matches batting first", "sp": "2018-2020", "mt": 8, "in": 8, "pr": "batting_fielding_first=1", "ov": 76, "cd": 369, "md": 7, "wk": 13, "fwk": 1, "fw": 0, "tw": 0, "bbi": "4/26", "bbm": "4/26", "bwa": 28.38, "bwe": 4.85, "bwsr": 35}, {"bl": null, "tt": "matches fielding first", "sp": "2018-2019", "mt": 5, "in": 5, "pr": "batting_fielding_first=2", "ov": 42, "cd": 321, "md": 4, "wk": 11, "fwk": 0, "fw": 0, "tw": 0, "bbi": "3/85", "bbm": "3/85", "bwa": 29.18, "bwe": 7.64, "bwsr": 22.9}]}, {"type": "TEAM_INNINGS", "stats": [{"bl": null, "tt": "1st team innings", "sp": "2018-2020", "mt": 13, "in": 13, "pr": "innings_number=2;innings_number=1", "ov": 118, "cd": 690, "md": 11, "wk": 24, "fwk": 1, "fw": 0, "tw": 0, "bbi": "4/26", "bbm": "4/26", "bwa": 28.75, "bwe": 5.84, "bwsr": 29.5}]}, {"type": "MATCH_INNINGS", "stats": [{"bl": null, "tt": "1st match innings", "sp": "2018-2019", "mt": 5, "in": 5, "pr": "innings_number=1", "ov": 42, "cd": 321, "md": 4, "wk": 11, "fwk": 0, "fw": 0, "tw": 0, "bbi": "3/85", "bbm": "3/85", "bwa": 29.18, "bwe": 7.64, "bwsr": 22.9}, {"bl": null, "tt": "2nd match innings", "sp": "2018-2020", "mt": 8, "in": 8, "pr": "innings_number=2", "ov": 76, "cd": 369, "md": 7, "wk": 13, "fwk": 1, "fw": 0, "tw": 0, "bbi": "4/26", "bbm": "4/26", "bwa": 28.38, "bwe": 4.85, "bwsr": 35}]}, {"type": "FLOODLIT", "stats": [{"bl": null, "tt": "day match", "sp": "2018-2020", "mt": 2, "in": 2, "pr": "floodlit=1", "ov": 20, "cd": 122, "md": 1, "wk": 2, "fwk": 0, "fw": 0, "tw": 0, "bbi": "2/64", "bbm": "2/64", "bwa": 61, "bwe": 6.1, "bwsr": 60}, {"bl": null, "tt": "day/night match", "sp": "2018-2019", "mt": 11, "in": 11, "pr": "floodlit=2", "ov": 98, "cd": 568, "md": 10, "wk": 22, "fwk": 1, "fw": 0, "tw": 0, "bbi": "4/26", "bbm": "4/26", "bwa": 25.81, "bwe": 5.79, "bwsr": 26.7}]}, {"type": "RESULT", "stats": [{"bl": null, "tt": "won match", "sp": "2019-2019", "mt": 6, "in": 6, "pr": "result=1", "ov": 51, "cd": 275, "md": 7, "wk": 15, "fwk": 1, "fw": 0, "tw": 0, "bbi": "4/26", "bbm": "4/26", "bwa": 18.33, "bwe": 5.39, "bwsr": 20.4}, {"bl": null, "tt": "lost match", "sp": "2018-2020", "mt": 7, "in": 7, "pr": "result=2", "ov": 67, "cd": 415, "md": 4, "wk": 9, "fwk": 0, "fw": 0, "tw": 0, "bbi": "3/92", "bbm": "3/92", "bwa": 46.11, "bwe": 6.19, "bwsr": 44.6}]}, {"type": "BATTING_FIELDING_SEQUENCE_AND_RESULT", "stats": [{"bl": null, "tt": "won batting first", "sp": "2019-2019", "mt": 3, "in": 3, "pr": "batting_fielding_first=1;result=1", "ov": 29, "cd": 110, "md": 4, "wk": 9, "fwk": 1, "fw": 0, "tw": 0, "bbi": "4/26", "bbm": "4/26", "bwa": 12.22, "bwe": 3.79, "bwsr": 19.3}, {"bl": null, "tt": "won fielding first", "sp": "2019-2019", "mt": 3, "in": 3, "pr": "batting_fielding_first=2;result=1", "ov": 22, "cd": 165, "md": 3, "wk": 6, "fwk": 0, "fw": 0, "tw": 0, "bbi": "3/85", "bbm": "3/85", "bwa": 27.5, "bwe": 7.5, "bwsr": 22}, {"bl": null, "tt": "lost batting first", "sp": "2018-2020", "mt": 5, "in": 5, "pr": "batting_fielding_first=1;result=2", "ov": 47, "cd": 259, "md": 3, "wk": 4, "fwk": 0, "fw": 0, "tw": 0, "bbi": "2/57", "bbm": "2/57", "bwa": 64.75, "bwe": 5.51, "bwsr": 70.5}, {"bl": null, "tt": "lost fielding first", "sp": "2018-2018", "mt": 2, "in": 2, "pr": "batting_fielding_first=2;result=2", "ov": 20, "cd": 156, "md": 1, "wk": 5, "fwk": 0, "fw": 0, "tw": 0, "bbi": "3/92", "bbm": "3/92", "bwa": 31.2, "bwe": 7.8, "bwsr": 24}]}, {"type": "TOURNAMENT_TYPE", "stats": [{"bl": null, "tt": "2 team series", "sp": "2018-2020", "mt": 13, "in": 13, "pr": "tournament_type=2", "ov": 118, "cd": 690, "md": 11, "wk": 24, "fwk": 1, "fw": 0, "tw": 0, "bbi": "4/26", "bbm": "4/26", "bwa": 28.75, "bwe": 5.84, "bwsr": 29.5}]}, {"type": "MATCH_NUMBER", "stats": [{"bl": null, "tt": "1st match in series", "sp": "2019-2019", "mt": 2, "in": 2, "pr": "match_number=1", "ov": 18, "cd": 90, "md": 3, "wk": 5, "fwk": 1, "fw": 0, "tw": 0, "bbi": "4/26", "bbm": "4/26", "bwa": 18, "bwe": 5, "bwsr": 21.6}, {"bl": null, "tt": "2nd match in series", "sp": "2018-2019", "mt": 4, "in": 4, "pr": "match_number=2", "ov": 35, "cd": 196, "md": 3, "wk": 7, "fwk": 0, "fw": 0, "tw": 0, "bbi": "2/16", "bbm": "2/16", "bwa": 28, "bwe": 5.6, "bwsr": 30}, {"bl": null, "tt": "3rd match in series", "sp": "2018-2020", "mt": 4, "in": 4, "pr": "match_number=3", "ov": 39, "cd": 214, "md": 5, "wk": 7, "fwk": 0, "fw": 0, "tw": 0, "bbi": "3/37", "bbm": "3/37", "bwa": 30.57, "bwe": 5.48, "bwsr": 33.4}, {"bl": null, "tt": "4th match in series", "sp": "2018-2019", "mt": 2, "in": 2, "pr": "match_number=4", "ov": 16, "cd": 143, "md": 0, "wk": 3, "fwk": 0, "fw": 0, "tw": 0, "bbi": "3/85", "bbm": "3/85", "bwa": 47.66, "bwe": 8.93, "bwsr": 32}, {"bl": null, "tt": "5th match in series", "sp": "2019-2019", "mt": 1, "in": 1, "pr": "match_number=5", "ov": 10, "cd": 47, "md": 0, "wk": 2, "fwk": 0, "fw": 0, "tw": 0, "bbi": "2/47", "bbm": "2/47", "bwa": 23.5, "bwe": 4.7, "bwsr": 30}]}, {"type": "BOWLING_POSITION", "stats": [{"bl": null, "tt": "1st position", "sp": "2018-2020", "mt": 5, "in": 5, "pr": "bowling_positionval1=bowling_position;bowling_positionmin1=1;bowling_positionmax1=1", "ov": 43, "cd": 229, "md": 5, "wk": 6, "fwk": 0, "fw": 0, "tw": 0, "bbi": "2/16", "bbm": "2/16", "bwa": 38.16, "bwe": 5.32, "bwsr": 43}, {"bl": null, "tt": "2nd position", "sp": "2018-2019", "mt": 6, "in": 6, "pr": "bowling_positionval1=bowling_position;bowling_positionmin1=2;bowling_positionmax1=2", "ov": 59, "cd": 318, "md": 6, "wk": 15, "fwk": 1, "fw": 0, "tw": 0, "bbi": "4/26", "bbm": "4/26", "bwa": 21.2, "bwe": 5.38, "bwsr": 23.6}, {"bl": null, "tt": "3rd position", "sp": "2019-2019", "mt": 1, "in": 1, "pr": "bowling_positionval1=bowling_position;bowling_positionmin1=3;bowling_positionmax1=3", "ov": 9, "cd": 85, "md": 0, "wk": 3, "fwk": 0, "fw": 0, "tw": 0, "bbi": "3/85", "bbm": "3/85", "bwa": 28.33, "bwe": 9.44, "bwsr": 18}, {"bl": null, "tt": "4th position", "sp": "2018-2018", "mt": 1, "in": 1, "pr": "bowling_positionval1=bowling_position;bowling_positionmin1=4;bowling_positionmax1=4", "ov": 7, "cd": 58, "md": 0, "wk": 0, "fwk": 0, "fw": 0, "tw": 0, "bbi": null, "bbm": null, "bwa": null, "bwe": 8.28, "bwsr": null}]}]}}