{"summary": {"recordClassId": 2, "type": "BATTING", "groups": [{"type": "CAREER_AVERAGES", "stats": [{"tt": "overview", "sp": "2015-2020", "mt": 33, "in": 14, "pr": null, "rn": 81, "fo": 4, "si": 4, "ft": 0, "hn": 0, "bf": 104, "dk": 4, "no": 3, "hs": "24", "bta": 7.36, "btsr": 77.88}]}, {"type": "OPPOSITION_TEAM", "stats": [{"tt": "vs Australia", "sp": "2016-2020", "mt": 3, "in": 3, "pr": "opposition=2", "rn": 19, "fo": 2, "si": 0, "ft": 0, "hn": 0, "bf": 21, "dk": 1, "no": 1, "hs": "14*", "bta": 9.5, "btsr": 90.47}, {"tt": "vs Bangladesh", "sp": "2017-2017", "mt": 1, "in": null, "pr": "opposition=25", "rn": null, "fo": null, "si": null, "ft": null, "hn": null, "bf": null, "dk": null, "no": null, "hs": null, "bta": null, "btsr": null}, {"tt": "vs England", "sp": "2018-2018", "mt": 4, "in": 2, "pr": "opposition=1", "rn": 7, "fo": 0, "si": 0, "ft": 0, "hn": 0, "bf": 10, "dk": 0, "no": 1, "hs": "5", "bta": 7, "btsr": 70}, {"tt": "vs India", "sp": "2016-2020", "mt": 6, "in": 4, "pr": "opposition=6", "rn": 13, "fo": 0, "si": 1, "ft": 0, "hn": 0, "bf": 28, "dk": 2, "no": 0, "hs": "12", "bta": 3.25, "btsr": 46.42}, {"tt": "vs Ireland", "sp": "2017-2017", "mt": 2, "in": null, "pr": "opposition=29", "rn": null, "fo": null, "si": null, "ft": null, "hn": null, "bf": null, "dk": null, "no": null, "hs": null, "bta": null, "btsr": null}, {"tt": "vs Pakistan", "sp": "2018-2018", "mt": 3, "in": 2, "pr": "opposition=7", "rn": 37, "fo": 2, "si": 3, "ft": 0, "hn": 0, "bf": 30, "dk": 0, "no": 0, "hs": "24", "bta": 18.5, "btsr": 123.33}, {"tt": "vs South Africa", "sp": "2015-2017", "mt": 5, "in": 2, "pr": "opposition=3", "rn": 5, "fo": 0, "si": 0, "ft": 0, "hn": 0, "bf": 15, "dk": 1, "no": 0, "hs": "5", "bta": 2.5, "btsr": 33.33}, {"tt": "vs Sri Lanka", "sp": "2015-2019", "mt": 6, "in": 1, "pr": "opposition=8", "rn": 0, "fo": 0, "si": 0, "ft": 0, "hn": 0, "bf": 0, "dk": 0, "no": 1, "hs": "0*", "bta": null, "btsr": null}, {"tt": "vs Zimbabwe", "sp": "2015-2015", "mt": 3, "in": null, "pr": "opposition=9", "rn": null, "fo": null, "si": null, "ft": null, "hn": null, "bf": null, "dk": null, "no": null, "hs": null, "bta": null, "btsr": null}]}, {"type": "HOST_COUNTRY", "stats": [{"tt": "in Australia", "sp": "2020-2020", "mt": 1, "in": 1, "pr": "host=2", "rn": 14, "fo": 1, "si": 0, "ft": 0, "hn": 0, "bf": 16, "dk": 0, "no": 1, "hs": "14*", "bta": null, "btsr": 87.5}, {"tt": "in England", "sp": "2019-2019", "mt": 1, "in": 1, "pr": "host=1", "rn": 5, "fo": 1, "si": 0, "ft": 0, "hn": 0, "bf": 4, "dk": 0, "no": 0, "hs": "5", "bta": 5, "btsr": 125}, {"tt": "in India", "sp": "2016-2016", "mt": 3, "in": 2, "pr": "host=6", "rn": 1, "fo": 0, "si": 0, "ft": 0, "hn": 0, "bf": 15, "dk": 1, "no": 0, "hs": "1", "bta": 0.5, "btsr": 6.66}, {"tt": "in Ireland", "sp": "2017-2017", "mt": 3, "in": null, "pr": "host=29", "rn": null, "fo": null, "si": null, "ft": null, "hn": null, "bf": null, "dk": null, "no": null, "hs": null, "bta": null, "btsr": null}, {"tt": "in New Zealand", "sp": "2015-2020", "mt": 16, "in": 6, "pr": "host=5", "rn": 19, "fo": 0, "si": 1, "ft": 0, "hn": 0, "bf": 24, "dk": 2, "no": 2, "hs": "12", "bta": 4.75, "btsr": 79.16}, {"tt": "in South Africa", "sp": "2015-2015", "mt": 3, "in": 2, "pr": "host=3", "rn": 5, "fo": 0, "si": 0, "ft": 0, "hn": 0, "bf": 15, "dk": 1, "no": 0, "hs": "5", "bta": 2.5, "btsr": 33.33}, {"tt": "in U.A.E.", "sp": "2018-2018", "mt": 3, "in": 2, "pr": "host=27", "rn": 37, "fo": 2, "si": 3, "ft": 0, "hn": 0, "bf": 30, "dk": 0, "no": 0, "hs": "24", "bta": 18.5, "btsr": 123.33}, {"tt": "in Zimbabwe", "sp": "2015-2015", "mt": 3, "in": null, "pr": "host=9", "rn": null, "fo": null, "si": null, "ft": null, "hn": null, "bf": null, "dk": null, "no": null, "hs": null, "bta": null, "btsr": null}]}, {"type": "CONTINENT", "stats": [{"tt": "in Africa", "sp": "2015-2015", "mt": 6, "in": 2, "pr": "continent=1", "rn": 5, "fo": 0, "si": 0, "ft": 0, "hn": 0, "bf": 15, "dk": 1, "no": 0, "hs": "5", "bta": 2.5, "btsr": 33.33}, {"tt": "in Asia", "sp": "2016-2018", "mt": 6, "in": 4, "pr": "continent=2", "rn": 38, "fo": 2, "si": 3, "ft": 0, "hn": 0, "bf": 45, "dk": 1, "no": 0, "hs": "24", "bta": 9.5, "btsr": 84.44}, {"tt": "in Europe", "sp": "2017-2019", "mt": 4, "in": 1, "pr": "continent=4", "rn": 5, "fo": 1, "si": 0, "ft": 0, "hn": 0, "bf": 4, "dk": 0, "no": 0, "hs": "5", "bta": 5, "btsr": 125}, {"tt": "in Oceania", "sp": "2015-2020", "mt": 17, "in": 7, "pr": "continent=5", "rn": 33, "fo": 1, "si": 1, "ft": 0, "hn": 0, "bf": 40, "dk": 2, "no": 3, "hs": "14*", "bta": 8.25, "btsr": 82.5}]}, {"type": "HOME_OR_AWAY", "stats": [{"tt": "home", "sp": "2015-2020", "mt": 16, "in": 6, "pr": "home_or_away=1", "rn": 19, "fo": 0, "si": 1, "ft": 0, "hn": 0, "bf": 24, "dk": 2, "no": 2, "hs": "12", "bta": 4.75, "btsr": 79.16}, {"tt": "away", "sp": "2015-2020", "mt": 12, "in": 5, "pr": "home_or_away=2", "rn": 20, "fo": 1, "si": 0, "ft": 0, "hn": 0, "bf": 46, "dk": 2, "no": 1, "hs": "14*", "bta": 5, "btsr": 43.47}, {"tt": "neutral", "sp": "2017-2019", "mt": 5, "in": 3, "pr": "home_or_away=3", "rn": 42, "fo": 3, "si": 3, "ft": 0, "hn": 0, "bf": 34, "dk": 0, "no": 0, "hs": "24", "bta": 14, "btsr": 123.52}]}, {"type": "YEAR", "stats": [{"tt": "year 2015", "sp": null, "mt": 7, "in": 2, "pr": "year=2015", "rn": 5, "fo": 0, "si": 0, "ft": 0, "hn": 0, "bf": 15, "dk": 1, "no": 0, "hs": "5", "bta": 2.5, "btsr": 33.33}, {"tt": "year 2016", "sp": null, "mt": 6, "in": 3, "pr": "year=2016", "rn": 1, "fo": 0, "si": 0, "ft": 0, "hn": 0, "bf": 16, "dk": 2, "no": 0, "hs": "1", "bta": 0.33, "btsr": 6.25}, {"tt": "year 2017", "sp": null, "mt": 5, "in": null, "pr": "year=2017", "rn": null, "fo": null, "si": null, "ft": null, "hn": null, "bf": null, "dk": null, "no": null, "hs": null, "bta": null, "btsr": null}, {"tt": "year 2018", "sp": null, "mt": 7, "in": 4, "pr": "year=2018", "rn": 44, "fo": 2, "si": 3, "ft": 0, "hn": 0, "bf": 40, "dk": 0, "no": 1, "hs": "24", "bta": 14.66, "btsr": 110}, {"tt": "year 2019", "sp": null, "mt": 6, "in": 4, "pr": "year=2019", "rn": 17, "fo": 1, "si": 1, "ft": 0, "hn": 0, "bf": 17, "dk": 1, "no": 1, "hs": "12", "bta": 5.66, "btsr": 100}, {"tt": "year 2020", "sp": null, "mt": 2, "in": 1, "pr": "year=2020", "rn": 14, "fo": 1, "si": 0, "ft": 0, "hn": 0, "bf": 16, "dk": 0, "no": 1, "hs": "14*", "bta": null, "btsr": 87.5}]}, {"type": "SEASON", "stats": [{"tt": "season 2015", "sp": null, "mt": 6, "in": 2, "pr": "season=2015", "rn": 5, "fo": 0, "si": 0, "ft": 0, "hn": 0, "bf": 15, "dk": 1, "no": 0, "hs": "5", "bta": 2.5, "btsr": 33.33}, {"tt": "season 2015/16", "sp": null, "mt": 4, "in": 1, "pr": "season=NaN", "rn": 0, "fo": 0, "si": 0, "ft": 0, "hn": 0, "bf": 1, "dk": 1, "no": 0, "hs": "0", "bta": 0, "btsr": 0}, {"tt": "season 2016/17", "sp": null, "mt": 5, "in": 2, "pr": "season=NaN", "rn": 1, "fo": 0, "si": 0, "ft": 0, "hn": 0, "bf": 15, "dk": 1, "no": 0, "hs": "1", "bta": 0.5, "btsr": 6.66}, {"tt": "season 2017", "sp": null, "mt": 3, "in": null, "pr": "season=2017", "rn": null, "fo": null, "si": null, "ft": null, "hn": null, "bf": null, "dk": null, "no": null, "hs": null, "bta": null, "btsr": null}, {"tt": "season 2017/18", "sp": null, "mt": 4, "in": 2, "pr": "season=NaN", "rn": 7, "fo": 0, "si": 0, "ft": 0, "hn": 0, "bf": 10, "dk": 0, "no": 1, "hs": "5", "bta": 7, "btsr": 70}, {"tt": "season 2018/19", "sp": null, "mt": 8, "in": 5, "pr": "season=NaN", "rn": 49, "fo": 2, "si": 4, "ft": 0, "hn": 0, "bf": 43, "dk": 1, "no": 1, "hs": "24", "bta": 12.25, "btsr": 113.95}, {"tt": "season 2019", "sp": null, "mt": 1, "in": 1, "pr": "season=2019", "rn": 5, "fo": 1, "si": 0, "ft": 0, "hn": 0, "bf": 4, "dk": 0, "no": 0, "hs": "5", "bta": 5, "btsr": 125}, {"tt": "season 2019/20", "sp": null, "mt": 2, "in": 1, "pr": "season=NaN", "rn": 14, "fo": 1, "si": 0, "ft": 0, "hn": 0, "bf": 16, "dk": 0, "no": 1, "hs": "14*", "bta": null, "btsr": 87.5}]}, {"type": "CAPTAINS_INVOLVED", "stats": [{"tt": "*TWM Latham", "sp": "2017-2020", "mt": 5, "in": null, "pr": "captain_involve=59148", "rn": null, "fo": null, "si": null, "ft": null, "hn": null, "bf": null, "dk": null, "no": null, "hs": null, "bta": null, "btsr": null}, {"tt": "*BB McCullum", "sp": "2015-2016", "mt": 2, "in": 1, "pr": "captain_involve=10384", "rn": 0, "fo": 0, "si": 0, "ft": 0, "hn": 0, "bf": 1, "dk": 1, "no": 0, "hs": "0", "bta": 0, "btsr": 0}, {"tt": "*KS Williamson", "sp": "2015-2020", "mt": 26, "in": 13, "pr": "captain_involve=51088", "rn": 81, "fo": 4, "si": 4, "ft": 0, "hn": 0, "bf": 103, "dk": 3, "no": 3, "hs": "24", "bta": 8.1, "btsr": 78.64}]}, {"type": "CAPTAIN", "stats": [{"tt": "is not captain", "sp": "2015-2020", "mt": 33, "in": 14, "pr": "captain=0", "rn": 81, "fo": 4, "si": 4, "ft": 0, "hn": 0, "bf": 104, "dk": 4, "no": 3, "hs": "24", "bta": 7.36, "btsr": 77.88}]}, {"type": "KEEPER", "stats": [{"tt": "is not keeper", "sp": "2015-2020", "mt": 33, "in": 14, "pr": "keeper=0", "rn": 81, "fo": 4, "si": 4, "ft": 0, "hn": 0, "bf": 104, "dk": 4, "no": 3, "hs": "24", "bta": 7.36, "btsr": 77.88}]}, {"type": "TOSS", "stats": [{"tt": "won the toss", "sp": "2015-2020", "mt": 12, "in": 6, "pr": "toss=1", "rn": 51, "fo": 2, "si": 4, "ft": 0, "hn": 0, "bf": 45, "dk": 1, "no": 2, "hs": "24", "bta": 12.75, "btsr": 113.33}, {"tt": "lost the toss", "sp": "2015-2020", "mt": 21, "in": 8, "pr": "toss=2", "rn": 30, "fo": 2, "si": 0, "ft": 0, "hn": 0, "bf": 59, "dk": 3, "no": 1, "hs": "14*", "bta": 4.28, "btsr": 50.84}]}, {"type": "BATTING_FIELDING_SEQUENCE_AND_TOSS", "stats": [{"tt": "won toss &amp; batted", "sp": "2016-2019", "mt": 6, "in": 4, "pr": "batting_fielding_first=1;toss=1", "rn": 49, "fo": 2, "si": 4, "ft": 0, "hn": 0, "bf": 42, "dk": 0, "no": 1, "hs": "24", "bta": 16.33, "btsr": 116.66}, {"tt": "won toss &amp; fielded", "sp": "2015-2020", "mt": 6, "in": 2, "pr": "batting_fielding_first=2;toss=1", "rn": 2, "fo": 0, "si": 0, "ft": 0, "hn": 0, "bf": 3, "dk": 1, "no": 1, "hs": "2*", "bta": 2, "btsr": 66.66}, {"tt": "lost toss &amp; sent in", "sp": "2015-2019", "mt": 12, "in": 3, "pr": "batting_fielding_first=1;toss=2", "rn": 6, "fo": 0, "si": 0, "ft": 0, "hn": 0, "bf": 18, "dk": 1, "no": 0, "hs": "5", "bta": 2, "btsr": 33.33}, {"tt": "lost toss &amp; fielded", "sp": "2015-2020", "mt": 9, "in": 5, "pr": "batting_fielding_first=2;toss=2", "rn": 24, "fo": 2, "si": 0, "ft": 0, "hn": 0, "bf": 41, "dk": 2, "no": 1, "hs": "14*", "bta": 6, "btsr": 58.53}]}, {"type": "BATTING_FIELDING_SEQUENCE", "stats": [{"tt": "matches batting first", "sp": "2015-2019", "mt": 18, "in": 7, "pr": "batting_fielding_first=1", "rn": 55, "fo": 2, "si": 4, "ft": 0, "hn": 0, "bf": 60, "dk": 1, "no": 1, "hs": "24", "bta": 9.16, "btsr": 91.66}, {"tt": "matches fielding first", "sp": "2015-2020", "mt": 15, "in": 7, "pr": "batting_fielding_first=2", "rn": 26, "fo": 2, "si": 0, "ft": 0, "hn": 0, "bf": 44, "dk": 3, "no": 2, "hs": "14*", "bta": 5.2, "btsr": 59.09}]}, {"type": "TEAM_INNINGS", "stats": [{"tt": "1st team innings", "sp": "2015-2020", "mt": 33, "in": 14, "pr": null, "rn": 81, "fo": 4, "si": 4, "ft": 0, "hn": 0, "bf": 104, "dk": 4, "no": 3, "hs": "24", "bta": 7.36, "btsr": 77.88}]}, {"type": "MATCH_INNINGS", "stats": [{"tt": "1st match innings", "sp": "2015-2019", "mt": 18, "in": 7, "pr": "innings_number=1", "rn": 55, "fo": 2, "si": 4, "ft": 0, "hn": 0, "bf": 60, "dk": 1, "no": 1, "hs": "24", "bta": 9.16, "btsr": 91.66}, {"tt": "2nd match innings", "sp": "2015-2020", "mt": 15, "in": 7, "pr": "innings_number=2", "rn": 26, "fo": 2, "si": 0, "ft": 0, "hn": 0, "bf": 44, "dk": 3, "no": 2, "hs": "14*", "bta": 5.2, "btsr": 59.09}]}, {"type": "FLOODLIT", "stats": [{"tt": "day match", "sp": "2015-2019", "mt": 14, "in": 1, "pr": "floodlit=1", "rn": 5, "fo": 0, "si": 0, "ft": 0, "hn": 0, "bf": 7, "dk": 0, "no": 0, "hs": "5", "bta": 5, "btsr": 71.42}, {"tt": "day/night match", "sp": "2015-2020", "mt": 19, "in": 13, "pr": "floodlit=2", "rn": 76, "fo": 4, "si": 4, "ft": 0, "hn": 0, "bf": 97, "dk": 4, "no": 3, "hs": "24", "bta": 7.6, "btsr": 78.35}]}, {"type": "RESULT", "stats": [{"tt": "won match", "sp": "2015-2020", "mt": 18, "in": 3, "pr": "result=1", "rn": 24, "fo": 1, "si": 2, "ft": 0, "hn": 0, "bf": 20, "dk": 1, "no": 1, "hs": "24", "bta": 12, "btsr": 120}, {"tt": "lost match", "sp": "2015-2020", "mt": 13, "in": 11, "pr": "result=2", "rn": 57, "fo": 3, "si": 2, "ft": 0, "hn": 0, "bf": 84, "dk": 3, "no": 2, "hs": "14*", "bta": 6.33, "btsr": 67.85}, {"tt": "no result", "sp": "2016-2018", "mt": 2, "in": null, "pr": "result=5", "rn": null, "fo": null, "si": null, "ft": null, "hn": null, "bf": null, "dk": null, "no": null, "hs": null, "bta": null, "btsr": null}]}, {"type": "BATTING_FIELDING_SEQUENCE_AND_RESULT", "stats": [{"tt": "won batting first", "sp": "2015-2019", "mt": 11, "in": 3, "pr": "batting_fielding_first=1;result=1", "rn": 24, "fo": 1, "si": 2, "ft": 0, "hn": 0, "bf": 20, "dk": 1, "no": 1, "hs": "24", "bta": 12, "btsr": 120}, {"tt": "won fielding first", "sp": "2015-2020", "mt": 7, "in": null, "pr": "batting_fielding_first=2;result=1", "rn": null, "fo": null, "si": null, "ft": null, "hn": null, "bf": null, "dk": null, "no": null, "hs": null, "bta": null, "btsr": null}, {"tt": "lost batting first", "sp": "2015-2019", "mt": 6, "in": 4, "pr": "batting_fielding_first=1;result=2", "rn": 31, "fo": 1, "si": 2, "ft": 0, "hn": 0, "bf": 40, "dk": 0, "no": 0, "hs": "13", "bta": 7.75, "btsr": 77.5}, {"tt": "lost fielding first", "sp": "2015-2020", "mt": 7, "in": 7, "pr": "batting_fielding_first=2;result=2", "rn": 26, "fo": 2, "si": 0, "ft": 0, "hn": 0, "bf": 44, "dk": 3, "no": 2, "hs": "14*", "bta": 5.2, "btsr": 59.09}, {"tt": "no result batting first", "sp": "2016-2016", "mt": 1, "in": null, "pr": "batting_fielding_first=1;result=5", "rn": null, "fo": null, "si": null, "ft": null, "hn": null, "bf": null, "dk": null, "no": null, "hs": null, "bta": null, "btsr": null}, {"tt": "no result fielding first", "sp": "2018-2018", "mt": 1, "in": null, "pr": "batting_fielding_first=2;result=5", "rn": null, "fo": null, "si": null, "ft": null, "hn": null, "bf": null, "dk": null, "no": null, "hs": null, "bta": null, "btsr": null}]}, {"type": "TOURNAMENT_TYPE", "stats": [{"tt": "2 team series", "sp": "2015-2020", "mt": 29, "in": 13, "pr": "tournament_type=2", "rn": 76, "fo": 3, "si": 4, "ft": 0, "hn": 0, "bf": 100, "dk": 4, "no": 3, "hs": "24", "bta": 7.6, "btsr": 76}, {"tt": "3-4 team tournaments", "sp": "2017-2017", "mt": 3, "in": null, "pr": "tournament_type=3", "rn": null, "fo": null, "si": null, "ft": null, "hn": null, "bf": null, "dk": null, "no": null, "hs": null, "bta": null, "btsr": null}, {"tt": "5+ team tournaments", "sp": "2019-2019", "mt": 1, "in": 1, "pr": "tournament_type=5", "rn": 5, "fo": 1, "si": 0, "ft": 0, "hn": 0, "bf": 4, "dk": 0, "no": 0, "hs": "5", "bta": 5, "btsr": 125}]}, {"type": "MATCH_NUMBER", "stats": [{"tt": "1st match in series", "sp": "2015-2020", "mt": 9, "in": 5, "pr": "match_number=1", "rn": 39, "fo": 2, "si": 2, "ft": 0, "hn": 0, "bf": 45, "dk": 1, "no": 2, "hs": "24", "bta": 13, "btsr": 86.66}, {"tt": "2nd match in series", "sp": "2015-2019", "mt": 7, "in": 2, "pr": "match_number=2", "rn": 13, "fo": 1, "si": 1, "ft": 0, "hn": 0, "bf": 12, "dk": 1, "no": 0, "hs": "13", "bta": 6.5, "btsr": 108.33}, {"tt": "3rd match in series", "sp": "2015-2019", "mt": 7, "in": 4, "pr": "match_number=3", "rn": 19, "fo": 0, "si": 1, "ft": 0, "hn": 0, "bf": 31, "dk": 1, "no": 1, "hs": "12", "bta": 6.33, "btsr": 61.29}, {"tt": "4th match in series", "sp": "2016-2018", "mt": 3, "in": null, "pr": "match_number=4", "rn": null, "fo": null, "si": null, "ft": null, "hn": null, "bf": null, "dk": null, "no": null, "hs": null, "bta": null, "btsr": null}, {"tt": "5th match in series", "sp": "2016-2018", "mt": 3, "in": 2, "pr": "match_number=5", "rn": 5, "fo": 0, "si": 0, "ft": 0, "hn": 0, "bf": 12, "dk": 1, "no": 0, "hs": "5", "bta": 2.5, "btsr": 41.66}]}, {"type": "MAJOR_TROPHY", "stats": [{"tt": "World Cup", "sp": "2019-2019", "mt": 1, "in": 1, "pr": "trophy=12", "rn": 5, "fo": 1, "si": 0, "ft": 0, "hn": 0, "bf": 4, "dk": 0, "no": 0, "hs": "5", "bta": 5, "btsr": 125}, {"tt": "Chappell-Hadlee", "sp": "2016-2020", "mt": 2, "in": 2, "pr": "trophy=65", "rn": 14, "fo": 1, "si": 0, "ft": 0, "hn": 0, "bf": 17, "dk": 1, "no": 1, "hs": "14*", "bta": 14, "btsr": 82.35}]}, {"type": "BATTING_POSITION", "stats": [{"tt": "9th position", "sp": "2018-2020", "mt": 7, "in": 7, "pr": "batting_positionval1=batting_position;batting_positionmin1=9;batting_positionmax1=9", "rn": 68, "fo": 4, "si": 4, "ft": 0, "hn": 0, "bf": 63, "dk": 1, "no": 2, "hs": "24", "bta": 13.6, "btsr": 107.93}, {"tt": "10th position", "sp": "2016-2018", "mt": 3, "in": 3, "pr": "batting_positionval1=batting_position;batting_positionmin1=10;batting_positionmax1=10", "rn": 7, "fo": 0, "si": 0, "ft": 0, "hn": 0, "bf": 15, "dk": 1, "no": 1, "hs": "5", "bta": 3.5, "btsr": 46.66}, {"tt": "11th position", "sp": "2015-2016", "mt": 4, "in": 4, "pr": "batting_positionval1=batting_position;batting_positionmin1=11;batting_positionmax1=11", "rn": 6, "fo": 0, "si": 0, "ft": 0, "hn": 0, "bf": 26, "dk": 2, "no": 0, "hs": "5", "bta": 1.5, "btsr": 23.07}]}]}}